README.rst
arxiv2bib.py
setup.cfg
setup.py
arxiv2bib.egg-info/PKG-INFO
arxiv2bib.egg-info/SOURCES.txt
arxiv2bib.egg-info/dependency_links.txt
arxiv2bib.egg-info/entry_points.txt
arxiv2bib.egg-info/top_level.txt