Metadata-Version: 1.1
Name: arxiv2bib
Version: 1.0.6
Summary: Get arXiv.org metadata in BibTeX format
Home-page: http://nathangrigg.github.io/arxiv2bib
Author: Nathan Grigg
Author-email: nathan@nathangrigg.net
License: BSD
Keywords: arxiv,bibtex,latex,citation
Platform: UNKNOWN
Classifier: Programming Language :: Python :: 2
Classifier: Programming Language :: Python :: 2.7
Classifier: Programming Language :: Python :: 3
Classifier: License :: OSI Approved :: BSD License
Classifier: Operating System :: OS Independent
Classifier: Development Status :: 5 - Production/Stable
Classifier: Intended Audience :: Science/Research
Classifier: Topic :: Text Processing :: Markup :: LaTeX
Classifier: Environment :: Console
